mac.v
// Created by prof. Mingu Kang @VVIP Lab in UCSD ECE department
// Please do not spread this code without permission 
module mac (out, a, b, c);

parameter a_bw = 2;
parameter b_bw = 4;
parameter psum_bw = 16;

output signed [psum_bw-1:0] out;
input signed  [a_bw-1:0] a;  // activation
input signed  [b_bw-1:0] b;  // weight
input signed  [psum_bw-1:0] c;


wire signed [2*b_bw:0] product;
wire signed [psum_bw-1:0] psum;
wire signed [a_bw:0]   a_pad;

assign a_pad = {2'b00, a}; // force to be unsigned number
assign product = a_pad * b;

assign psum = product + c;
assign out = psum;

endmodule

mac_tile.v
// Created by prof. Mingu Kang @VVIP Lab in UCSD ECE department
// Please do not spread this code without permission 
module mac_tile (clk, 
	out_s0, out_s1, in_w0, in_w1, out_e0, out_e1, in_n0, in_n1, 
	inst_w, inst_e, reset);

parameter bw = 2;
parameter psum_bw = 9;

// dual psum output, dual 2bit input moving act, etc.
input  [psum_bw-1:0] in_n0;
input  [psum_bw-1:0] in_n1;

output [psum_bw-1:0] out_s0;
output [psum_bw-1:0] out_s1;

input  [bw-1:0] in_w0; 
input  [bw-1:0] in_w1; 

output [bw-1:0] out_e0; 
output [bw-1:0] out_e1; 

// 2 bit kernel loading instruction, 1 bit execution, 1 bit mode?
input  [2:0] inst_w;
output [2:0] inst_e;
// mode will always propagate, execution will always propagate,
// kernel loading depends.

input  clk;
input  reset;

reg [bw-1:0] a_q0;
reg [bw-1:0] a_q1;
reg [4-1:0] b_q0;
reg [4-1:0] b_q1;
reg [psum_bw-1:0] c_q0;
reg [psum_bw-1:0] c_q1;
reg [2:0] inst_q;
reg [1:0] load_ready_q;

wire [psum_bw-1:0] mac_output0;
wire [psum_bw-1:0] mac_output1;

assign out_e0[bw-1:0] = a_q0[bw-1:0];
assign out_e1[bw-1:0] = a_q1[bw-1:0];

assign inst_e[2:0] = inst_q[2:0];


// inst_e[0] = left or right reg

// inst_e[2] = mode. 1 = 4bit mode, 0 = 2bit mode
// inst_e[1] = exec
// inst_e[0] = weightload

wire [10:0] big_psum;
// wire [1:0] lsb_sign;
// assign lsb_sign = {mac_output0[8], mac_output0[8]};
assign big_psum = {{2{mac_output0[8]}}, mac_output0} 
	+ {mac_output1, 2'b0};

// assign from big psum if STORED mode is 1 else just pull from mac output
assign out_s0 = inst_q[2] ? {1'b0, big_psum[7:0]} : mac_output0[psum_bw-1:0];
//assign out_s1 = inst_q[2] ? {2'b0, big_psum[10:8], 4'b0} : mac_output1[psum_bw-1:0];
assign out_s1 = inst_q[2] ? {big_psum[10:8], 6'b0} : mac_output1[psum_bw-1:0];


mac #(.a_bw(bw), .b_bw(4), .psum_bw(psum_bw)) mac_instance0 (
        .a(a_q0), 
        .b(b_q0),
        .c(c_q0),
	.out(mac_output0)
); 

mac #(.a_bw(bw), .b_bw(4), .psum_bw(psum_bw)) mac_instance1 (
        .a(a_q1), 
        .b(b_q1),
        .c(c_q1),
	.out(mac_output1)
); 

always@(posedge clk) begin
	
	if(reset==1'b1)	begin
		// i feel like reset should clear everything...
		inst_q <= 0;
		load_ready_q <= 2'b11; //weight not loaded yet
	end

	else begin

		// weight loading portion

		inst_q[2:1] <= inst_w[2:1];	// each cycle forward the MODE bit and EXECUTE bit.

		c_q0[psum_bw-1:0] <= in_n0[psum_bw-1:0]; // psum from previous mac used as c in a*b +c
		c_q1[psum_bw-1:0] <= in_n1[psum_bw-1:0]; // psum from previous mac used as c in a*b +c

		if (inst_w[1:0] != 2'b00) // if we are executing or loading weights, move the data in
			a_q0<=in_w0;
			a_q1<=in_w1;
		if ((inst_w[2] == 1'b0) && (inst_w[0] == 1'b1)) begin // 0 mode = 2-bit mode, 
			if (load_ready_q[0]) begin
				b_q0 <= {in_w1, in_w0};
				load_ready_q[0] <= 1'b0;
			end
			else if (load_ready_q[1]) begin
				b_q1 <= {in_w1, in_w0};
				load_ready_q[1] <= 1'b0;
			end
		end
	 	if ((inst_w[2] == 1'b1) && (inst_w[0] == 1'b1) && (load_ready_q == 2'b11)) begin // 1 mode = 4bit mode, load weights into both simultaneously.
			b_q0<={in_w1, in_w0};
			b_q1<={in_w1, in_w0};
			load_ready_q <= 2'b00;
		end
		
		if(load_ready_q == 2'b00) begin //weight loaded then move kernel instruction
			inst_q[0] <= inst_w[0];
		end
	end
end

endmodule

mac_row.v
// Created by prof. Mingu Kang @VVIP Lab in UCSD ECE department
// Please do not spread this code without permission 
module mac_row (clk, out_s, in_w0, in_w1, in_n, valid, inst_w, reset);

	parameter bw = 2;
	parameter psum_bw = 9;
	parameter col = 8;
	parameter inst_bw = 3;

	input  clk, reset;
	// out_s for dual psum output
	output [psum_bw*col*2-1:0] out_s;
	output [col-1:0] valid;
	input  [bw-1:0] in_w0; 
	input  [bw-1:0] in_w1; 
	input  [inst_bw-1:0] inst_w; // inst[1]:execute, inst[0]: kernel loading
	input  [psum_bw*col*2-1:0] in_n;

	wire  [(col+1)*bw-1:0] temp0;
	wire  [(col+1)*bw-1:0] temp1;
	
	wire  [(col+1)*inst_bw-1:0] inst;
	
	assign temp0[bw-1:0] = in_w0;
	assign temp1[bw-1:0] = in_w1;

	assign inst[inst_bw-1:0] = inst_w[inst_bw-1:0];

	/*
	mac_tile (clk, reset
		out_s0, out_s1, in_w0, in_w1, 
		out_e0, out_e1, in_n0, in_n1, 
		inst_w, inst_e, );
	*/

	/*
		// inst_w/e[2] = mode. 1 = 4bit mode, 0 = 2bit mode
		// inst_w/e[1] = exec
		// inst_w/e[0] = weightload
	*/

	genvar i;
	for (i=0; i < col; i=i+1) begin : col_num
		mac_tile #(.bw(bw), .psum_bw(psum_bw)) mac_tile_instance (
			.clk(clk),
			.reset(reset),
			.in_w0(temp0[bw*(i+1)-1:bw*i]),
			.in_w1(temp1[bw*(i+1)-1:bw*i]),
			.out_e0(temp0[bw*(i+2)-1:bw*(i+1)]),
			.out_e1(temp1[bw*(i+2)-1:bw*(i+1)]),

			// fix below? is this fine??
			// in this manner, we can have entire psum row output right???
			.in_n0(in_n[psum_bw*(2*i+1)-1:psum_bw*i*2]),
			.in_n1(in_n[psum_bw*(2*i+2)-1:psum_bw*(2*i+1)]),
			.out_s0(out_s[psum_bw*(2*i+1)-1:psum_bw*i*2]),
			.out_s1(out_s[psum_bw*(2*i+2)-1:psum_bw*(2*i+1)]),
			
			// this is fine
			.inst_w(inst[inst_bw*(i+1)-1:inst_bw*i]),
			.inst_e(inst[inst_bw*(i+2)-1:inst_bw*(i+1)]));
			// valid is the exec bit passing through. -1 = mode -2 = exec
		// valid flag when the dual psum is ready.
		assign valid[i] = inst[inst_bw*(i+2)-2];
	end

endmodule

mac_row_tb.v
module mac_row_tb;

parameter bw = 2;
parameter psum_bw = 9;
parameter inst_bw = 3;
parameter col = 4;

// test with 4 columns first for ease of reading

// send reset signal to mac_tile

reg clk;
reg reset;

// (clk, reset, out_s, in_w, in_n, inst_w, valid);

// inputs
reg [bw-1:0] in_w0;
reg [bw-1:0] in_w1;
reg [psum_bw*col*2-1:0] in_n;
reg [inst_bw-1:0] inst_w;

// outputs
wire [psum_bw*col*2-1:0] out_s;
wire [col-1:0] valid;

mac_row #(bw, psum_bw, col, inst_bw) uut (
    .clk(clk),
    .out_s(out_s),
    .in_w0(in_w0),
    .in_w1(in_w1),
    .in_n(in_n),
    .inst_w(inst_w),
    .reset(reset)
);


reg [col*2-1:0][psum_bw-1:0] out_display;

// Clock generation
initial begin
    clk = 0;
    forever #5 clk = ~clk; // 10 time units clock period
end

integer j;

always @(negedge clk) begin
    out_display <= out_s;
end

always @(posedge clk) begin
    $display("psum outputs:");
    for (j = 0; j < col*2; j = j + 1) begin
        $display("out_s[%0d]: %0d", j, $signed(out_display[j]));
    end
    $display("-----------------------");
end;

integer i;

// Testbench procedure
initial begin

    $dumpfile("mac_row_tb.vcd");
    $dumpvars(0, mac_row_tb);
    // Initialize inputs

    reset = 1;
    in_n = 0;
    in_w0 = 0;
    in_w1 = 0;
    inst_w = 0;
    #10;
    reset = 0;

    // CASE 1 : 2-bit mode operation
    // Load weight for 2-bit mode. Repeat 8 times (two for each column) for 4 columns
    inst_w = 3'b001; // mode=0, exec=0, weight
    // value = 0001 = 1
    in_w0 = 2'b01; 
    in_w1 = 2'b00;
    #10;

    // value = 0010 = 2;
    in_w0 = 2'b10; 
    in_w1 = 2'b00; 
    #10;
    
    // value = 0011 = 3;
    in_w0 = 2'b11; 
    in_w1 = 2'b00; 
    #10;

    // value = 0100 = 4;
    in_w0 = 2'b00; 
    in_w1 = 2'b10; 
    #10;
    
    // value = 1000 = -8;
    in_w0 = 2'b00; 
    in_w1 = 2'b10; 
    #10;

    // value = 0000 = 0;
    in_w0 = 2'b00;
    in_w1 = 2'b00;
    #10;
    
    // value = 1000 = -7;
    in_w0 = 2'b01; 
    in_w1 = 2'b10; 
    #10;

    // value = 1000 = 7;
    in_w0 = 2'b11; 
    in_w1 = 2'b01; 
    #10;

    // all weights are loaded, begin mac operations
    inst_w = 3'b010; // mode=0, exec=1, weightload=0

    // pass in activations of -8 to 7 sequentially
    for (i = 0; i < 16; i = i + 1) begin
        {in_w1, in_w0} = i;
        #10;
    end


    // man too tired.. just believe that it works
    #80;
    
    $finish;
end

endmodule

mac_row_tb.vcd
$date
	Thu Nov 27 00:07:50 2025
$end
$version
	Icarus Verilog
$end
$timescale
	1s
$end
$scope module mac_row_tb $end
$var wire 72 ! out_s [71:0] $end
$var parameter 32 " bw $end
$var parameter 32 # col $end
$var parameter 32 $ inst_bw $end
$var parameter 32 % psum_bw $end
$var reg 1 & clk $end
$var reg 72 ' in_n [71:0] $end
$var reg 2 ( in_w0 [1:0] $end
$var reg 2 ) in_w1 [1:0] $end
$var reg 3 * inst_w [2:0] $end
$var reg 72 + out_display [71:0] $end
$var reg 1 , reset $end
$var integer 32 - i [31:0] $end
$var integer 32 . j [31:0] $end
$scope module uut $end
$var wire 1 & clk $end
$var wire 72 / in_n [71:0] $end
$var wire 2 0 in_w0 [1:0] $end
$var wire 2 1 in_w1 [1:0] $end
$var wire 3 2 inst_w [2:0] $end
$var wire 1 , reset $end
$var wire 4 3 valid [3:0] $end
$var wire 10 4 temp1 [9:0] $end
$var wire 10 5 temp0 [9:0] $end
$var wire 72 6 out_s [71:0] $end
$var wire 15 7 inst [14:0] $end
$var parameter 32 8 bw $end
$var parameter 32 9 col $end
$var parameter 32 : inst_bw $end
$var parameter 32 ; psum_bw $end
$scope begin col_num[0] $end
$var parameter 2 < i $end
$scope module mac_tile_instance $end
$var wire 1 & clk $end
$var wire 9 = in_n0 [8:0] $end
$var wire 9 > in_n1 [8:0] $end
$var wire 2 ? in_w0 [1:0] $end
$var wire 2 @ in_w1 [1:0] $end
$var wire 3 A inst_e [2:0] $end
$var wire 3 B inst_w [2:0] $end
$var wire 2 C out_e0 [1:0] $end
$var wire 2 D out_e1 [1:0] $end
$var wire 1 , reset $end
$var wire 9 E out_s1 [8:0] $end
$var wire 9 F out_s0 [8:0] $end
$var wire 9 G mac_output1 [8:0] $end
$var wire 9 H mac_output0 [8:0] $end
$var wire 11 I big_psum [10:0] $end
$var parameter 32 J bw $end
$var parameter 32 K psum_bw $end
$var reg 2 L a_q0 [1:0] $end
$var reg 2 M a_q1 [1:0] $end
$var reg 4 N b_q0 [3:0] $end
$var reg 4 O b_q1 [3:0] $end
$var reg 9 P c_q0 [8:0] $end
$var reg 9 Q c_q1 [8:0] $end
$var reg 3 R inst_q [2:0] $end
$var reg 2 S load_ready_q [1:0] $end
$scope module mac_instance0 $end
$var wire 2 T a [1:0] $end
$var wire 4 U b [3:0] $end
$var wire 9 V c [8:0] $end
$var wire 9 W out [8:0] $end
$var wire 9 X psum [8:0] $end
$var wire 9 Y product [8:0] $end
$var wire 3 Z a_pad [2:0] $end
$var parameter 32 [ a_bw $end
$var parameter 32 \ b_bw $end
$var parameter 32 ] psum_bw $end
$upscope $end
$scope module mac_instance1 $end
$var wire 2 ^ a [1:0] $end
$var wire 4 _ b [3:0] $end
$var wire 9 ` c [8:0] $end
$var wire 9 a out [8:0] $end
$var wire 9 b psum [8:0] $end
$var wire 9 c product [8:0] $end
$var wire 3 d a_pad [2:0] $end
$var parameter 32 e a_bw $end
$var parameter 32 f b_bw $end
$var parameter 32 g psum_bw $end
$upscope $end
$upscope $end
$upscope $end
$scope begin col_num[1] $end
$var parameter 2 h i $end
$scope module mac_tile_instance $end
$var wire 1 & clk $end
$var wire 9 i in_n0 [8:0] $end
$var wire 9 j in_n1 [8:0] $end
$var wire 2 k in_w0 [1:0] $end
$var wire 2 l in_w1 [1:0] $end
$var wire 3 m inst_e [2:0] $end
$var wire 3 n inst_w [2:0] $end
$var wire 2 o out_e0 [1:0] $end
$var wire 2 p out_e1 [1:0] $end
$var wire 1 , reset $end
$var wire 9 q out_s1 [8:0] $end
$var wire 9 r out_s0 [8:0] $end
$var wire 9 s mac_output1 [8:0] $end
$var wire 9 t mac_output0 [8:0] $end
$var wire 11 u big_psum [10:0] $end
$var parameter 32 v bw $end
$var parameter 32 w psum_bw $end
$var reg 2 x a_q0 [1:0] $end
$var reg 2 y a_q1 [1:0] $end
$var reg 4 z b_q0 [3:0] $end
$var reg 4 { b_q1 [3:0] $end
$var reg 9 | c_q0 [8:0] $end
$var reg 9 } c_q1 [8:0] $end
$var reg 3 ~ inst_q [2:0] $end
$var reg 2 !" load_ready_q [1:0] $end
$scope module mac_instance0 $end
$var wire 2 "" a [1:0] $end
$var wire 4 #" b [3:0] $end
$var wire 9 $" c [8:0] $end
$var wire 9 %" out [8:0] $end
$var wire 9 &" psum [8:0] $end
$var wire 9 '" product [8:0] $end
$var wire 3 (" a_pad [2:0] $end
$var parameter 32 )" a_bw $end
$var parameter 32 *" b_bw $end
$var parameter 32 +" psum_bw $end
$upscope $end
$scope module mac_instance1 $end
$var wire 2 ," a [1:0] $end
$var wire 4 -" b [3:0] $end
$var wire 9 ." c [8:0] $end
$var wire 9 /" out [8:0] $end
$var wire 9 0" psum [8:0] $end
$var wire 9 1" product [8:0] $end
$var wire 3 2" a_pad [2:0] $end
$var parameter 32 3" a_bw $end
$var parameter 32 4" b_bw $end
$var parameter 32 5" psum_bw $end
$upscope $end
$upscope $end
$upscope $end
$scope begin col_num[2] $end
$var parameter 3 6" i $end
$scope module mac_tile_instance $end
$var wire 1 & clk $end
$var wire 9 7" in_n0 [8:0] $end
$var wire 9 8" in_n1 [8:0] $end
$var wire 2 9" in_w0 [1:0] $end
$var wire 2 :" in_w1 [1:0] $end
$var wire 3 ;" inst_e [2:0] $end
$var wire 3 <" inst_w [2:0] $end
$var wire 2 =" out_e0 [1:0] $end
$var wire 2 >" out_e1 [1:0] $end
$var wire 1 , reset $end
$var wire 9 ?" out_s1 [8:0] $end
$var wire 9 @" out_s0 [8:0] $end
$var wire 9 A" mac_output1 [8:0] $end
$var wire 9 B" mac_output0 [8:0] $end
$var wire 11 C" big_psum [10:0] $end
$var parameter 32 D" bw $end
$var parameter 32 E" psum_bw $end
$var reg 2 F" a_q0 [1:0] $end
$var reg 2 G" a_q1 [1:0] $end
$var reg 4 H" b_q0 [3:0] $end
$var reg 4 I" b_q1 [3:0] $end
$var reg 9 J" c_q0 [8:0] $end
$var reg 9 K" c_q1 [8:0] $end
$var reg 3 L" inst_q [2:0] $end
$var reg 2 M" load_ready_q [1:0] $end
$scope module mac_instance0 $end
$var wire 2 N" a [1:0] $end
$var wire 4 O" b [3:0] $end
$var wire 9 P" c [8:0] $end
$var wire 9 Q" out [8:0] $end
$var wire 9 R" psum [8:0] $end
$var wire 9 S" product [8:0] $end
$var wire 3 T" a_pad [2:0] $end
$var parameter 32 U" a_bw $end
$var parameter 32 V" b_bw $end
$var parameter 32 W" psum_bw $end
$upscope $end
$scope module mac_instance1 $end
$var wire 2 X" a [1:0] $end
$var wire 4 Y" b [3:0] $end
$var wire 9 Z" c [8:0] $end
$var wire 9 [" out [8:0] $end
$var wire 9 \" psum [8:0] $end
$var wire 9 ]" product [8:0] $end
$var wire 3 ^" a_pad [2:0] $end
$var parameter 32 _" a_bw $end
$var parameter 32 `" b_bw $end
$var parameter 32 a" psum_bw $end
$upscope $end
$upscope $end
$upscope $end
$scope begin col_num[3] $end
$var parameter 3 b" i $end
$scope module mac_tile_instance $end
$var wire 1 & clk $end
$var wire 9 c" in_n0 [8:0] $end
$var wire 9 d" in_n1 [8:0] $end
$var wire 2 e" in_w0 [1:0] $end
$var wire 2 f" in_w1 [1:0] $end
$var wire 3 g" inst_e [2:0] $end
$var wire 3 h" inst_w [2:0] $end
$var wire 2 i" out_e0 [1:0] $end
$var wire 2 j" out_e1 [1:0] $end
$var wire 1 , reset $end
$var wire 9 k" out_s1 [8:0] $end
$var wire 9 l" out_s0 [8:0] $end
$var wire 9 m" mac_output1 [8:0] $end
$var wire 9 n" mac_output0 [8:0] $end
$var wire 11 o" big_psum [10:0] $end
$var parameter 32 p" bw $end
$var parameter 32 q" psum_bw $end
$var reg 2 r" a_q0 [1:0] $end
$var reg 2 s" a_q1 [1:0] $end
$var reg 4 t" b_q0 [3:0] $end
$var reg 4 u" b_q1 [3:0] $end
$var reg 9 v" c_q0 [8:0] $end
$var reg 9 w" c_q1 [8:0] $end
$var reg 3 x" inst_q [2:0] $end
$var reg 2 y" load_ready_q [1:0] $end
$scope module mac_instance0 $end
$var wire 2 z" a [1:0] $end
$var wire 4 {" b [3:0] $end
$var wire 9 |" c [8:0] $end
$var wire 9 }" out [8:0] $end
$var wire 9 ~" psum [8:0] $end
$var wire 9 !# product [8:0] $end
$var wire 3 "# a_pad [2:0] $end
$var parameter 32 ## a_bw $end
$var parameter 32 $# b_bw $end
$var parameter 32 %# psum_bw $end
$upscope $end
$scope module mac_instance1 $end
$var wire 2 &# a [1:0] $end
$var wire 4 '# b [3:0] $end
$var wire 9 (# c [8:0] $end
$var wire 9 )# out [8:0] $end
$var wire 9 *# psum [8:0] $end
$var wire 9 +# product [8:0] $end
$var wire 3 ,# a_pad [2:0] $end
$var parameter 32 -# a_bw $end
$var parameter 32 .# b_bw $end
$var parameter 32 /# psum_bw $end
$upscope $end
$upscope $end
$upscope $end
$upscope $end
$upscope $end
$enddefinitions $end
$comment Show the parameter values. $end
$dumpall
b1001 /#
b100 .#
b10 -#
b1001 %#
b100 $#
b10 ##
b1001 q"
b10 p"
b11 b"
b1001 a"
b100 `"
b10 _"
b1001 W"
b100 V"
b10 U"
b1001 E"
b10 D"
b10 6"
b1001 5"
b100 4"
b10 3"
b1001 +"
b100 *"
b10 )"
b1001 w
b10 v
b1 h
b1001 g
b100 f
b10 e
b1001 ]
b100 \
b10 [
b1001 K
b10 J
b0 <
b1001 ;
b11 :
b100 9
b10 8
b1001 %
b11 $
b100 #
b10 "
$end
#0
$dumpvars
b0xx ,#
bx +#
bx *#
bx )#
bx (#
bx '#
bx &#
b0xx "#
bx !#
bx ~"
bx }"
bx |"
bx {"
bx z"
bx y"
bx x"
bx w"
bx v"
bx u"
bx t"
bx s"
bx r"
bx o"
bx n"
bx m"
bx l"
bx k"
bx j"
bx i"
bx h"
bx g"
bx f"
bx e"
b0 d"
b0 c"
b0xx ^"
bx ]"
bx \"
bx ["
bx Z"
bx Y"
bx X"
b0xx T"
bx S"
bx R"
bx Q"
bx P"
bx O"
bx N"
bx M"
bx L"
bx K"
bx J"
bx I"
bx H"
bx G"
bx F"
bx C"
bx B"
bx A"
bx @"
bx ?"
bx >"
bx ="
bx <"
bx ;"
bx :"
bx 9"
b0 8"
b0 7"
b0xx 2"
bx 1"
bx 0"
bx /"
bx ."
bx -"
bx ,"
b0xx ("
bx '"
bx &"
bx %"
bx $"
bx #"
bx ""
bx !"
bx ~
bx }
bx |
bx {
bx z
bx y
bx x
bx u
bx t
bx s
bx r
bx q
bx p
bx o
bx n
bx m
bx l
bx k
b0 j
b0 i
b0xx d
bx c
bx b
bx a
bx `
bx _
bx ^
b0xx Z
bx Y
bx X
bx W
bx V
bx U
bx T
bx S
bx R
bx Q
bx P
bx O
bx N
bx M
bx L
bx I
bx H
bx G
bx F
bx E
bx D
bx C
b0 B
bx A
b0 @
b0 ?
b0 >
b0 =
bx000 7
bx 6
bx00 5
bx00 4
bx 3
b0 2
b0 1
b0 0
b0 /
bx .
bx -
1,
bx +
b0 *
b0 )
b0 (
b0 '
0&
bx !
$end
#5
b0 n
b0 <"
b0 h"
b0 3
b11 S
b0 A
b0 R
b11 !"
b0 m
b0 ~
b11 M"
b0 ;"
b0 L"
b11 y"
b0 7
b0 g"
b0 x"
b1000 .
1&
#10
b1 ?
b1 B
0&
bx01 5
b1 (
b1 0
b1 7
b1 *
b1 2
0,
#15
bx000000001 !
bx000000001 6
b1 F
b0 d
b0 l
b1 H
b1 W
b1 X
b1 Y
b1 Z
b1 k
b0 w"
b0 (#
b0 v"
b0 |"
b0 K"
b0 Z"
b0 J"
b0 P"
b0 }
b0 ."
b0 |
b0 $"
b10 S
b1 N
b1 U
bx0000 4
b0 D
b0 M
b0 ^
bx0101 5
b1 C
b1 L
b1 T
b0 Q
b0 `
b0 P
b0 V
b1000 .
1&
#20
bx000000001 +
b10 ?
0&
bx0110 5
b10 (
b10 0
#25
b10 F
bx000000000000000010 !
bx000000000000000010 6
b0 E
b10 H
b10 W
b10 X
b10 Y
b10 Z
b10 k
b0 2"
b0 :"
b0 S
b10 I
b0 G
b0 a
b0 b
b0 c
b10 O
b10 _
bx1010 5
b10 C
b10 L
b10 T
bx000000 4
b0 p
b0 y
b0 ,"
b1000 .
1&
#30
bx000000000000000010 +
b11 ?
0&
bx1011 5
b11 (
b11 0
#35
bx000000000000000011 !
bx000000000000000011 6
b11 F
b0 ^"
b0 f"
b1 n
b11 I
b11 H
b11 W
b11 X
b11 Y
b11 Z
b11 k
bx00000000 4
b0 >"
b0 G"
b0 X"
b1001 7
b1 A
b1 R
bx1111 5
b11 C
b11 L
b11 T
b1000 .
1&
#40
bx000000000000000011 +
b10 @
b0 ?
0&
bx00000010 4
b10 )
b10 1
bx1100 5
b0 (
b0 0
#45
b100 E
b0 F
bx000001001000000100000000000 !
bx000001001000000100000000000 6
b1001 r
b100 G
b100 a
b100 b
b100 c
b10 d
b10 l
b10000 I
b0 H
b0 W
b0 X
b0 Y
b0 Z
b0 k
b1001 t
b1001 %"
b1001 &"
b1001 '"
b11 ("
b11 9"
b0 ,#
b10 D
b10 M
b10 ^
b0 C
b0 L
b0 T
b10 !"
b11 z
b11 #"
bx110000 5
b11 o
b11 x
b11 ""
b1010 4
b0 j"
b0 s"
b0 &#
b1000 .
1&
#50
bx000001001000000100000000000 +
0&
#55
b0 r
bx111110000000000000000000100000000000 !
bx111110000000000000000000100000000000 6
b111110000 q
b10 2"
b10 :"
b0 t
b0 %"
b0 &"
b0 '"
b0 ("
b0 9"
b0 !"
b11111000000 u
b111110000 s
b111110000 /"
b111110000 0"
b111110000 1"
b1000 {
b1000 -"
b101010 4
b10 p
b10 y
b10 ,"
bx000000 5
b0 o
b0 x
b0 ""
b1000 .
1&
#60
bx111110000000000000000000100000000000 +
b0 @
0&
b101000 4
b0 )
b0 1
#65
bx111110000000000000000000000000000000 !
bx111110000000000000000000000000000000 6
b0 E
b0 I
b0 G
b0 a
b0 b
b0 c
b0 d
b0 l
b1 <"
b10 ^"
b10 f"
b0 D
b0 M
b0 ^
b1001001 7
b1 m
b1 ~
b10100000 4
b10 >"
b10 G"
b10 X"
b1000 .
1&
#70
bx111110000000000000000000000000000000 +
b10 @
b1 ?
0&
b10100010 4
b10 )
b10 1
bx000001 5
b1 (
b1 0
#75
b0 @"
b0 q
b100 E
bx000000000000000000000000000000000100000000001 !
bx000000000000000000000000000000000100000000001 6
b1 F
b10 ,#
b0 B"
b0 Q"
b0 R"
b0 S"
b0 T"
b0 e"
b0 u
b0 s
b0 /"
b0 0"
b0 1"
b0 2"
b0 :"
b100 G
b100 a
b100 b
b100 c
b10 d
b10 l
b10001 I
b1 H
b1 W
b1 X
b1 Y
b1 Z
b1 k
b10 j"
b10 s"
b10 &#
b10 M"
b1000 H"
b1000 O"
b0 ="
b0 F"
b0 N"
b0 p
b0 y
b0 ,"
b1010001010 4
b10 D
b10 M
b10 ^
bx00000101 5
b1 C
b1 L
b1 T
b1000 .
1&
#80
bx000000000000000000000000000000000100000000001 +
b1 @
b11 ?
0&
b1010001001 4
b1 )
b1 1
bx00000111 5
b11 (
b11 0
#85
b10 E
b11 F
b111110000 q
b11 r
b10 G
b10 a
b10 b
b10 c
b1 d
b1 l
b1011 I
b11 H
b11 W
b11 X
b11 Y
b11 Z
b11 k
b111110000 s
b111110000 /"
b111110000 0"
b111110000 1"
b10 2"
b10 :"
b11111000011 u
b11 t
b11 %"
b11 &"
b11 '"
b1 ("
b1 9"
bx000000000000000000111110000000000011000000010000000011 !
bx000000000000000000111110000000000011000000010000000011 6
b0 ?"
b0 ^"
b0 f"
b1 D
b1 M
b1 ^
b11 C
b11 L
b11 T
b10 p
b10 y
b10 ,"
bx00011111 5
b1 o
b1 x
b1 ""
b0 M"
b0 C"
b0 A"
b0 ["
b0 \"
b0 ]"
b0 I"
b0 Y"
b1000100101 4
b0 >"
b0 G"
b0 X"
b1000 .
1&
#90
bx000000000000000000111110000000000011000000010000000011 +
b0 @
b0 ?
b10 B
0&
b1000100100 4
b0 )
b0 1
bx00011100 5
b0 (
b0 0
b0 -
b1001010 7
b10 *
b10 2
#95
b111111000 @"
b111111000 q
b1001 r
b0 E
bx000000000111111000111111000000001001000000000000000000 !
bx000000000111111000111111000000001001000000000000000000 6
b0 F
b0 ,#
b1 h"
b10 ^"
b10 f"
b11111111000 C"
b111111000 B"
b111111000 Q"
b111111000 R"
b111111000 S"
b1 T"
b1 e"
b111111000 s
b111111000 /"
b111111000 0"
b111111000 1"
b1 2"
b1 :"
b11111101001 u
b1001 t
b1001 %"
b1001 &"
b1001 '"
b11 ("
b11 9"
b0 G
b0 a
b0 b
b0 c
b0 d
b0 l
b0 I
b0 H
b0 W
b0 X
b0 Y
b0 Z
b0 k
b10 n
b1 3
b0 j"
b0 s"
b0 &#
b1 ;"
b1 L"
b10 >"
b10 G"
b10 X"
b1 ="
b1 F"
b1 N"
b1 p
b1 y
b1 ,"
b11 o
b11 x
b11 ""
b10010000 4
b0 D
b0 M
b0 ^
bx01110000 5
b0 C
b0 L
b0 T
b1001010010 7
b10 A
b10 R
b1000 .
1&
#100
bx000000000111111000111111000000001001000000000000000000 +
b1 ?
0&
bx01110001 5
b1 (
b1 0
b1 -
#105
b1 F
b0 q
b0 r
b111101000 @"
bx111111001000000000111101000000000000000000000000000000000000001 !
bx111111001000000000111101000000000000000000000000000000000000001 6
b111111001 l"
b1 I
b1 H
b1 W
b1 X
b1 Y
b1 Z
b1 k
b0 s
b0 /"
b0 0"
b0 1"
b0 2"
b0 :"
b0 u
b0 t
b0 %"
b0 &"
b0 '"
b0 ("
b0 9"
b10 <"
b11 3
b1 ^"
b1 f"
b11111101000 C"
b111101000 B"
b111101000 Q"
b111101000 R"
b111101000 S"
b11 T"
b11 e"
b10 ,#
b111111001 n"
b111111001 }"
b111111001 ~"
b111111001 !#
b1 "#
b1 C
b1 L
b1 T
b0 p
b0 y
b0 ,"
b0 o
b0 x
b0 ""
b1010010010 7
b10 m
b10 ~
b1 >"
b1 G"
b1 X"
b11 ="
b11 F"
b11 N"
b10 y"
b1001 t"
b1001 {"
b1001000000 4
b10 j"
b10 s"
b10 &#
b111000101 5
b1 i"
b1 r"
b1 z"
b1000 .
1&
#110
bx111111001000000000111101000000000000000000000000000000000000001 +
b10 ?
0&
b111000110 5
b10 (
b10 0
b10 -
#115
b111101011 l"
b0 @"
b11 r
b10 F
b111111101011000000000000000000000000000000000011000000000000000010 !
b111111101011000000000000000000000000000000000011000000000000000010 6
b111 k"
b1 ,#
b111101011 n"
b111101011 }"
b111101011 ~"
b111101011 !#
b11 "#
b0 ^"
b0 f"
b0 C"
b0 B"
b0 Q"
b0 R"
b0 S"
b0 T"
b0 e"
b10 h"
b111 3
b11 u
b11 t
b11 %"
b11 &"
b11 '"
b1 ("
b1 9"
b10 I
b10 H
b10 W
b10 X
b10 Y
b10 Z
b10 k
b0 y"
b111 o"
b111 m"
b111 )#
b111 *#
b111 +#
b111 u"
b111 '#
b1 j"
b1 s"
b1 &#
b11 i"
b11 r"
b11 z"
b100000000 4
b0 >"
b0 G"
b0 X"
b0 ="
b0 F"
b0 N"
b10010010010 7
b10 ;"
b10 L"
b1 o
b1 x
b1 ""
b1100011010 5
b10 C
b10 L
b10 T
b1000 .
1&
#120
b111111101011000000000000000000000000000000000011000000000000000010 +
b11 ?
0&
b1100011011 5
b11 (
b11 0
b11 -
#125
b11 F
b110 r
b111111000 @"
b0 k"
b111111000000000000000000110000000000000000011 !
b111111000000000000000000110000000000000000011 6
b0 l"
b11 I
b11 H
b11 W
b11 X
b11 Y
b11 Z
b11 k
b110 u
b110 t
b110 %"
b110 &"
b110 '"
b10 ("
b10 9"
b11111111000 C"
b111111000 B"
b111111000 Q"
b111111000 R"
b111111000 S"
b1 T"
b1 e"
b0 m"
b0 )#
b0 *#
b0 +#
b0 ,#
b0 o"
b0 n"
b0 }"
b0 ~"
b0 !#
b0 "#
b1111 3
b11 C
b11 L
b11 T
b10 o
b10 x
b10 ""
b1 ="
b1 F"
b1 N"
b0 4
b0 j"
b0 s"
b0 &#
b1101111 5
b0 i"
b0 r"
b0 z"
b10010010010010 7
b10 g"
b10 x"
b1000 .
1&
#130
b111111000000000000000000110000000000000000011 +
b1 @
b0 ?
0&
b1 4
b1 )
b1 1
b1101100 5
b0 (
b0 0
b100 -
