mac.v
// Created by prof. Mingu Kang @VVIP Lab in UCSD ECE department
// Please do not spread this code without permission 
module mac (out, a, b, c);

parameter a_bw = 2;
parameter b_bw = 4;
parameter psum_bw = 16;

output signed [psum_bw-1:0] out;
input signed  [a_bw-1:0] a;  // activation
input signed  [b_bw-1:0] b;  // weight
input signed  [psum_bw-1:0] c;


wire signed [2*b_bw:0] product;
wire signed [psum_bw-1:0] psum;
wire signed [a_bw:0]   a_pad;

assign a_pad = {2'b00, a}; // force to be unsigned number
assign product = a_pad * b;

assign psum = product + c;
assign out = psum;

endmodule

mac_tile.v
// Created by prof. Mingu Kang @VVIP Lab in UCSD ECE department
// Please do not spread this code without permission 
module mac_tile (clk, 
	out_s0, out_s1, in_w0, in_w1, out_e0, out_e1, in_n0, in_n1, 
	inst_w, inst_e, reset);

parameter bw = 2;
parameter psum_bw = 9;

// dual psum output, dual 2bit input moving act, etc.
input  [psum_bw-1:0] in_n0;
input  [psum_bw-1:0] in_n1;

output [psum_bw-1:0] out_s0;
output [psum_bw-1:0] out_s1;

input  [bw-1:0] in_w0; 
input  [bw-1:0] in_w1; 

output [bw-1:0] out_e0; 
output [bw-1:0] out_e1; 

// 2 bit kernel loading instruction, 1 bit execution, 1 bit mode?
input  [2:0] inst_w;
output [2:0] inst_e;
// mode will always propagate, execution will always propagate,
// kernel loading depends.

input  clk;
input  reset;

reg [bw-1:0] a_q0;
reg [bw-1:0] a_q1;
reg [4-1:0] b_q0;
reg [4-1:0] b_q1;
reg [psum_bw-1:0] c_q0;
reg [psum_bw-1:0] c_q1;
reg [2:0] inst_q;
reg [1:0] load_ready_q;

wire [psum_bw-1:0] mac_output0;
wire [psum_bw-1:0] mac_output1;

assign out_e0[bw-1:0] = a_q0[bw-1:0];
assign out_e1[bw-1:0] = a_q1[bw-1:0];

assign inst_e[2:0] = inst_q[2:0];


// inst_e[0] = left or right reg

// inst_e[2] = mode. 1 = 4bit mode, 0 = 2bit mode
// inst_e[1] = exec
// inst_e[0] = weightload

wire [10:0] big_psum;
// wire [1:0] lsb_sign;
// assign lsb_sign = {mac_output0[8], mac_output0[8]};
assign big_psum = {{2{mac_output0[8]}}, mac_output0} 
	+ {mac_output1, 2'b0};

// assign from big psum if STORED mode is 1 else just pull from mac output
assign out_s0 = inst_q[2] ? {1'b0, big_psum[7:0]} : mac_output0[psum_bw-1:0];
//assign out_s1 = inst_q[2] ? {2'b0, big_psum[10:8], 4'b0} : mac_output1[psum_bw-1:0];
assign out_s1 = inst_q[2] ? {big_psum[10:8], 6'b0} : mac_output1[psum_bw-1:0];


mac #(.a_bw(bw), .b_bw(4), .psum_bw(psum_bw)) mac_instance0 (
        .a(a_q0), 
        .b(b_q0),
        .c(c_q0),
	.out(mac_output0)
); 

mac #(.a_bw(bw), .b_bw(4), .psum_bw(psum_bw)) mac_instance1 (
        .a(a_q1), 
        .b(b_q1),
        .c(c_q1),
	.out(mac_output1)
); 

always@(posedge clk) begin
	
	if(reset==1'b1)	begin
		// i feel like reset should clear everything...
		inst_q <= 0;
		load_ready_q <= 2'b11; //weight not loaded yet
	end

	else begin

		// weight loading portion

		inst_q[2:1] <= inst_w[2:1];	// each cycle forward the MODE bit and EXECUTE bit.

		c_q0[psum_bw-1:0] <= in_n0[psum_bw-1:0]; // psum from previous mac used as c in a*b +c
		c_q1[psum_bw-1:0] <= in_n1[psum_bw-1:0]; // psum from previous mac used as c in a*b +c

		if (inst_w[1:0] != 2'b00) // if we are executing or loading weights, move the data in
			a_q0<=in_w0;
			a_q1<=in_w1;
		if ((inst_w[2] == 1'b0) && (inst_w[0] == 1'b1)) begin // 0 mode = 2-bit mode, 
			if (load_ready_q[0]) begin
				b_q0 <= {in_w1, in_w0};
				load_ready_q[0] <= 1'b0;
			end
			else if (load_ready_q[1]) begin
				b_q1 <= {in_w1, in_w0};
				load_ready_q[1] <= 1'b0;
			end
		end
	 	if ((inst_w[2] == 1'b1) && (inst_w[0] == 1'b1) && (load_ready_q == 2'b11)) begin // 1 mode = 4bit mode, load weights into both simultaneously.
			b_q0<={in_w1, in_w0};
			b_q1<={in_w1, in_w0};
			load_ready_q <= 2'b00;
		end
		
		if(load_ready_q == 2'b00) begin //weight loaded then move kernel instruction
			inst_q[0] <= inst_w[0];
		end
	end
end

endmodule

legacy/mac_tile_tb.v
module mac_tile_tb;

parameter bw = 2;
parameter psum_bw = 9;

// send reset signal to mac_tile

reg clk;
reg reset;
reg [psum_bw-1:0] in_n0;
reg [psum_bw-1:0] in_n1;
reg [bw-1:0] in_w0;
reg [bw-1:0] in_w1;
reg [2:0] inst_w;
wire [psum_bw-1:0] out_s0;
wire [psum_bw-1:0] out_s1;
wire [bw-1:0] out_e0;
wire [bw-1:0] out_e1;
wire [2:0] inst_e;
mac_tile #(bw, psum_bw) uut (
    .clk(clk),
    .out_s0(out_s0),
    .out_s1(out_s1),
    .in_w0(in_w0),
    .in_w1(in_w1),
    .out_e0(out_e0),
    .out_e1(out_e1),
    .in_n0(in_n0),
    .in_n1(in_n1),
    .inst_w(inst_w),
    .inst_e(inst_e),
    .reset(reset)
);
// Clock generation
initial begin
    clk = 0;
    forever #5 clk = ~clk; // 10 time units clock period
end

// Testbench procedure
initial begin

    $dumpfile("mac_tile_tb.vcd");
    $dumpvars(0, mac_tile_tb);
    // Initialize inputs
    reset = 1;
    in_n0 = 0;
    in_n1 = 0;
    in_w0 = 0;
    in_w1 = 0;
    inst_w = 0;

    #10;
    reset = 0;

    // CASE 1 : 2-bit mode operation
    // Load weight for 2-bit mode
    inst_w = 3'b001; // mode=0, exec=0, weightload=1
    
    // weight 0 value: 1001 = -7
    in_w0 = 2'b01; // weight 0, 0
    in_w1 = 2'b10; // weight 0, 1
    
    #10; // Wait for one clock cycle

    inst_w = 3'b001; // mode=0, exec=0, weightload=1
    
    // weight 1 value: 0111 = 7
    in_w0 = 2'b11; // weight 1, 0
    in_w1 = 2'b01; // weight 1, 1

    #10; // Wait for one clock cycle

    // Execute MAC operation
    inst_w = 3'b010; // mode=0, exec=1, weightload=0
    in_w0 = 2'b10; 
    in_w1 = 2'b10;

    in_n0 = 9'b0; // psum input
    in_n1 = 9'b0; // psum input
    // expected output: -7*2+0=-14 , 7*2+0=14

    #10; // Wait for one clock cycle
    inst_w = 3'b010; // mode=0, exec=1, weightload=0
    in_w0 = 2'b11; 
    in_w1 = 2'b00;

    in_n0 = 9'd21; // psum input
    in_n1 = 9'd50; // psum input
    // expected output: -7*3+21=0 , 7*0+50=50

    #10; // Wait for one clock cycle
    inst_w = 3'b010; // mode=0, exec=1, weightload=0
    in_w0 = 2'b01; 
    in_w1 = 2'b11;

    in_n0 = 9'b0; // psum input
    in_n1 = 9'b100111111; // psum input
    // expected output: -7*1+0=-7 , 7*3+(-193)=-172

    #10; // Wait for one clock cycle
    inst_w = 3'b000; // dummy cycle
    in_w0 = 2'b01; 
    in_w1 = 2'b11;

    in_n0 = 9'b0; // psum input
    in_n1 = 9'b100111111; // psum input
    // expect no output change

    #10; 
    reset = 1; // reset before next test case

    // CASE 2 : 4-bit mode operation

    #10;
    reset = 0;

    // Load weight for 4-bit mode
    inst_w = 3'b101; // mode=1, exec=0, weightload=1
    // weight value: 1110 = -2
    in_w0 = 2'b10; // weight 0
    in_w1 = 2'b11; // weight 1

    #10; // Wait for one clock cycle
    // mac operation
    inst_w = 3'b110; // mode=1, exec=1, weightload=0
    // act value: 0111 = 7
    in_w0 = 2'b11;
    in_w1 = 2'b01;
    in_n0 = 9'b0; // psum input
    in_n1 = 9'b0; // psum input
    // mac_output0 = -2*3=-6 = 9'b111111010 
    // mac_output1 = -2*1=-2 = 9'b111111110 
    /*
      11111111010
    + 11111111000

    */
    // expected output: out_s0 = -2*7+0=-14, out_s1 = 0

    #10; // Wait for one clock cycle
    inst_w = 3'b110; // mode=1, exec=1, weightload=0
    // act_value = 1001 = 9 (unsigned)
    in_w0 = 2'b01;
    in_w1 = 2'b10;
    // in_psum = {513=11'b01000000001}
    // split into two parts for the inputs

    in_n0 = {1'b0, 8'b00000001}; // psum input = 243, 243+(1*-7) = 236
    in_n1 = {3'b010, 6'b0}; // psum input = 16 << 2 = 64
    // expected output: 495 = 00111101111

    #20;
    
    $finish;
end

endmodule

mac_tile_tb.vcd
$date
	Wed Nov 26 18:33:27 2025
$end
$version
	Icarus Verilog
$end
$timescale
	1s
$end
$scope module mac_tile_tb $end
$var wire 9 ! out_s1 [8:0] $end
$var wire 9 " out_s0 [8:0] $end
$var wire 2 # out_e1 [1:0] $end
$var wire 2 $ out_e0 [1:0] $end
$var wire 3 % inst_e [2:0] $end
$var parameter 32 & bw $end
$var parameter 32 ' psum_bw $end
$var reg 1 ( clk $end
$var reg 9 ) in_n0 [8:0] $end
$var reg 9 * in_n1 [8:0] $end
$var reg 2 + in_w0 [1:0] $end
$var reg 2 , in_w1 [1:0] $end
$var reg 3 - inst_w [2:0] $end
$var reg 1 . reset $end
$scope module uut $end
$var wire 1 ( clk $end
$var wire 9 / in_n0 [8:0] $end
$var wire 9 0 in_n1 [8:0] $end
$var wire 2 1 in_w0 [1:0] $end
$var wire 2 2 in_w1 [1:0] $end
$var wire 3 3 inst_e [2:0] $end
$var wire 3 4 inst_w [2:0] $end
$var wire 2 5 out_e0 [1:0] $end
$var wire 2 6 out_e1 [1:0] $end
$var wire 1 . reset $end
$var wire 9 7 out_s1 [8:0] $end
$var wire 9 8 out_s0 [8:0] $end
$var wire 9 9 mac_output1 [8:0] $end
$var wire 9 : mac_output0 [8:0] $end
$var wire 11 ; big_psum [10:0] $end
$var parameter 32 < bw $end
$var parameter 32 = psum_bw $end
$var reg 2 > a_q0 [1:0] $end
$var reg 2 ? a_q1 [1:0] $end
$var reg 4 @ b_q0 [3:0] $end
$var reg 4 A b_q1 [3:0] $end
$var reg 9 B c_q0 [8:0] $end
$var reg 9 C c_q1 [8:0] $end
$var reg 3 D inst_q [2:0] $end
$var reg 2 E load_ready_q [1:0] $end
$scope module mac_instance0 $end
$var wire 2 F a [1:0] $end
$var wire 4 G b [3:0] $end
$var wire 9 H c [8:0] $end
$var wire 9 I out [8:0] $end
$var wire 9 J psum [8:0] $end
$var wire 9 K product [8:0] $end
$var wire 3 L a_pad [2:0] $end
$var parameter 32 M a_bw $end
$var parameter 32 N b_bw $end
$var parameter 32 O psum_bw $end
$upscope $end
$scope module mac_instance1 $end
$var wire 2 P a [1:0] $end
$var wire 4 Q b [3:0] $end
$var wire 9 R c [8:0] $end
$var wire 9 S out [8:0] $end
$var wire 9 T psum [8:0] $end
$var wire 9 U product [8:0] $end
$var wire 3 V a_pad [2:0] $end
$var parameter 32 W a_bw $end
$var parameter 32 X b_bw $end
$var parameter 32 Y psum_bw $end
$upscope $end
$upscope $end
$upscope $end
$enddefinitions $end
$comment Show the parameter values. $end
$dumpall
b1001 Y
b100 X
b10 W
b1001 O
b100 N
b10 M
b1001 =
b10 <
b1001 '
b10 &
$end
#0
$dumpvars
b0xx V
bx U
bx T
bx S
bx R
bx Q
bx P
b0xx L
bx K
bx J
bx I
bx H
bx G
bx F
bx E
bx D
bx C
bx B
bx A
bx @
bx ?
bx >
bx ;
bx :
bx 9
bx 8
bx 7
bx 6
bx 5
b0 4
bx 3
b0 2
b0 1
b0 0
b0 /
1.
b0 -
b0 ,
b0 +
b0 *
b0 )
0(
bx %
bx $
bx #
bx "
bx !
$end
#5
b11 E
b0 %
b0 3
b0 D
1(
#10
0(
b10 ,
b10 2
b1 +
b1 1
b1 -
b1 4
0.
#15
b111111001 "
b111111001 8
b10 V
b111111001 :
b111111001 I
b111111001 J
b111111001 K
b1 L
b10 E
b1001 @
b1001 G
b10 #
b10 6
b10 ?
b10 P
b1 $
b1 5
b1 >
b1 F
b0 C
b0 R
b0 B
b0 H
1(
#20
0(
b1 ,
b1 2
b11 +
b11 1
#25
b111101011 "
b111101011 8
b111 !
b111 7
b1 V
b111101011 :
b111101011 I
b111101011 J
b111101011 K
b11 L
b0 E
b111 ;
b111 9
b111 S
b111 T
b111 U
b111 A
b111 Q
b1 #
b1 6
b1 ?
b1 P
b11 $
b11 5
b11 >
b11 F
1(
#30
0(
b10 ,
b10 2
b10 +
b10 1
b10 -
b10 4
#35
b1110 !
b1110 7
b111110010 "
b111110010 8
b1110 9
b1110 S
b1110 T
b1110 U
b10 V
b101010 ;
b111110010 :
b111110010 I
b111110010 J
b111110010 K
b10 L
b10 #
b10 6
b10 ?
b10 P
b10 $
b10 5
b10 >
b10 F
b10 %
b10 3
b10 D
1(
#40
0(
b110010 *
b110010 0
b10101 )
b10101 /
b0 ,
b0 2
b11 +
b11 1
#45
b0 U
b0 V
b111101011 K
b11 L
b110010 !
b110010 7
b0 "
b0 8
b0 #
b0 6
b0 ?
b0 P
b11 $
b11 5
b11 >
b11 F
b110010 9
b110010 S
b110010 T
b110010 C
b110010 R
b11001000 ;
b0 :
b0 I
b0 J
b10101 B
b10101 H
1(
#50
0(
b100111111 *
b100111111 0
b0 )
b0 /
b11 ,
b11 2
b1 +
b1 1
#55
b10101 U
b11 V
b111111001 K
b1 L
b101010100 !
b101010100 7
b111111001 "
b111111001 8
b11 #
b11 6
b11 ?
b11 P
b1 $
b1 5
b1 >
b1 F
b101010100 9
b101010100 S
b101010100 T
b100111111 C
b100111111 R
b10101001001 ;
b111111001 :
b111111001 I
b111111001 J
b0 B
b0 H
1(
#60
0(
b0 -
b0 4
#65
b0 %
b0 3
b0 D
1(
#70
0(
1.
#75
b11 E
1(
#80
0(
b10 +
b10 1
b101 -
b101 4
0.
#85
b1000000 !
b1000000 7
b11100000 "
b11100000 8
b10 L
b0 E
b100111001 9
b100111001 S
b100111001 T
b111111010 U
b1110 A
b1110 Q
b10011100000 ;
b111111100 :
b111111100 I
b111111100 J
b111111100 K
b1110 @
b1110 G
b10 $
b10 5
b10 >
b10 F
b100 %
b100 3
b100 D
1(
#90
0(
b0 *
b0 0
b1 ,
b1 2
b11 +
b11 1
b110 -
b110 4
#95
b11110010 "
b11110010 8
b1110000 !
b1110000 7
b111111110 U
b1 V
b111111010 :
b111111010 I
b111111010 J
b111111010 K
b11 L
b1 #
b1 6
b1 ?
b1 P
b11 $
b11 5
b11 >
b11 F
b11111110010 ;
b111111110 9
b111111110 S
b111111110 T
b0 C
b0 R
b110 %
b110 3
b110 D
1(
#100
0(
b10000000 *
b10000000 0
b1 )
b1 /
b10 ,
b10 2
b1 +
b1 1
#105
b10000 !
b10000 7
b11101111 "
b11101111 8
b111111100 U
b10 V
b111111110 K
b1 L
b10 #
b10 6
b10 ?
b10 P
b1 $
b1 5
b1 >
b1 F
b1111100 9
b1111100 S
b1111100 T
b10000000 C
b10000000 R
b111101111 ;
b111111111 :
b111111111 I
b111111111 J
b1 B
b1 H
1(
